odoo/addons/partner_auto_archive/README.rst
odoo/addons/partner_auto_archive/__init__.py
odoo/addons/partner_auto_archive/__manifest__.py
odoo/addons/partner_auto_archive/data/ir_cron.xml
odoo/addons/partner_auto_archive/i18n/de.po
odoo/addons/partner_auto_archive/i18n/it.po
odoo/addons/partner_auto_archive/i18n/partner_auto_archive.pot
odoo/addons/partner_auto_archive/models/__init__.py
odoo/addons/partner_auto_archive/models/res_partner.py
odoo/addons/partner_auto_archive/readme/CONTRIBUTORS.rst
odoo/addons/partner_auto_archive/readme/DESCRIPTION.rst
odoo/addons/partner_auto_archive/readme/USAGE.rst
odoo/addons/partner_auto_archive/static/description/icon.png
odoo/addons/partner_auto_archive/static/description/index.html
odoo/addons/partner_auto_archive/tests/__init__.py
odoo/addons/partner_auto_archive/tests/test_partner_auto_archive.py
odoo/addons/partner_auto_archive/views/res_partner_views.xml
odoo_addon_partner_auto_archive-16.0.1.0.0.6.dist-info/METADATA
odoo_addon_partner_auto_archive-16.0.1.0.0.6.dist-info/WHEEL
odoo_addon_partner_auto_archive-16.0.1.0.0.6.dist-info/top_level.txt
odoo_addon_partner_auto_archive-16.0.1.0.0.6.dist-info/RECORD
